{
    "Submodels" : {
        "vgg10_A" : {
                "model_path" : "models/multi_dnn/vgg10/models/radioml_own_trained.onnx",
                "specialize_layers_config_file" : "models/multi_dnn/vgg10/vgg10_specialize_layers.json"
            },
        "vgg10_B" : {
                "model_path" : "models/multi_dnn/vgg10/models/radioml_finn_trained.onnx",
                "specialize_layers_config_file" : "models/multi_dnn/vgg10/vgg10_specialize_layers.json"
            }
    },
    "Steps": [
        {"step_tidy_up": ["vgg10_A", "vgg10_B"]},
        {"finn.builder.custom_step_library.conv1d.step_pre_streamline": ["vgg10_A", "vgg10_B"]},
        {"step_streamline": ["vgg10_A", "vgg10_B"]},
        {"step_convert_to_hw": ["vgg10_A", "vgg10_B"]},
        {"finn.builder.custom_step_library.conv1d.step_convert_final_layers": ["vgg10_A", "vgg10_B"]},
        {"step_create_dataflow_partition": ["vgg10_A", "vgg10_B"]},
        {"step_specialize_layers": ["vgg10_A", "vgg10_B"]},
        {"step_apply_multi_dnn": "Multi_DNN_Wrapper"},
        {"step_collapse_multi_dnn": "Multi_DNN_Wrapper"},
        {"step_target_fps_parallelization": "Collapsed_Model"},
        {"step_apply_folding_config": "Collapsed_Model"},
        {"step_minimize_bit_width": "Collapsed_Model"},
        {"step_generate_estimate_reports": "Collapsed_Model"},
        {"step_prepare_nodecontainer": "Collapsed_Model"},
        {"step_set_fifo_depths": "Collapsed_Model"},
        {"step_hw_codegen": "Collapsed_Model"},
        {"step_hw_ipgen": "Collapsed_Model"},
        {"step_create_stitched_ip": "Collapsed_Model"},
        {"step_measure_rtlsim_performance": "Collapsed_Model"},
        {"step_out_of_context_synthesis": "Collapsed_Model"},
        {"step_synthesize_bitfile": "Collapsed_Model"},
        {"step_make_driver": "Collapsed_Model"},
        {"step_deployment_package": "Collapsed_Model"}
    ],
    "Generation" : {
        "mode" : "PartialReconfiguration",
        "kwargs" : {
            "reference_model_name": "vgg10_A",
            "pr_regions" : {
                "pr_mvau_0" : {
                    "vgg10_A" : ["MVAU_hls_0", "Thresholding_rtl_0"],
                    "vgg10_B" : ["MVAU_hls_0", "Thresholding_rtl_0"],
                    "pblock" : "SLICE_X46Y0:SLICE_X60Y59 DSP48E2_X8Y0:DSP48E2_X10Y23 RAMB18_X5Y0:RAMB18_X5Y23 RAMB36_X5Y0:RAMB36_X5Y11"
                },
                "pr_mvau_1" : {
                    "vgg10_A" : ["MVAU_hls_1", "Thresholding_hls_0"],
                    "vgg10_B" : ["MVAU_hls_1", "Thresholding_hls_0"],
                    "pblock" : "SLICE_X31Y60:SLICE_X60Y179 DSP48E2_X4Y24:DSP48E2_X10Y71 FE_X0Y1:FE_X0Y2 RAMB18_X3Y24:RAMB18_X5Y71 RAMB36_X3Y12:RAMB36_X5Y35"
                },
                "pr_mvau_2" : {
                    "vgg10_A" : ["MVAU_hls_2", "Thresholding_hls_1"],
                    "vgg10_B" : ["MVAU_hls_2", "Thresholding_hls_1"],
                    "pblock" : "SLICE_X46Y180:SLICE_X60Y299 DSP48E2_X8Y72:DSP48E2_X10Y119 RAMB18_X5Y72:RAMB18_X5Y119 RAMB36_X5Y36:RAMB36_X5Y59"
                },
                "pr_mvau_3" : {
                    "vgg10_A" : ["MVAU_hls_3", "Thresholding_hls_2"],
                    "vgg10_B" : ["MVAU_hls_3", "Thresholding_hls_2"],
                    "pblock" : "SLICE_X61Y300:SLICE_X78Y359 DSP48E2_X11Y120:DSP48E2_X13Y143 RAMB18_X6Y120:RAMB18_X7Y143 RAMB36_X6Y60:RAMB36_X7Y71"
                },
                "pr_mvau_4" : {
                    "vgg10_A" : ["MVAU_hls_4", "Thresholding_hls_3"],
                    "vgg10_B" : ["MVAU_hls_4", "Thresholding_hls_3"],
                    "pblock" : "SLICE_X86Y60:SLICE_X96Y119 DSP48E2_X16Y24:DSP48E2_X18Y47 RAMB18_X9Y24:RAMB18_X9Y47 RAMB36_X9Y12:RAMB36_X9Y23"
                },
                "pr_mvau_5" : {
                    "vgg10_A" : ["MVAU_hls_5", "Thresholding_hls_4"],
                    "vgg10_B" : ["MVAU_hls_5", "Thresholding_hls_4"],
                    "pblock" : "SLICE_X86Y120:SLICE_X94Y179 DSP48E2_X16Y48:DSP48E2_X18Y71 RAMB18_X9Y48:RAMB18_X9Y71 RAMB36_X9Y24:RAMB36_X9Y35"
                },
                "pr_mvau_6" : {
                    "vgg10_A" : ["MVAU_hls_6", "Thresholding_hls_5"],
                    "vgg10_B" : ["MVAU_hls_6", "Thresholding_hls_5"],
                    "pblock" : "SLICE_X86Y240:SLICE_X93Y299 DSP48E2_X16Y96:DSP48E2_X17Y119 RAMB18_X9Y96:RAMB18_X9Y119 RAMB36_X9Y48:RAMB36_X9Y59"
                },
                "pr_mvau_7" : {
                    "vgg10_A" : ["MVAU_hls_7", "Thresholding_hls_6", "MVAU_hls_8", "Thresholding_hls_7", "MVAU_hls_9", "ElementwiseAdd_hls_0"],
                    "vgg10_B" : ["MVAU_hls_7", "Thresholding_hls_6", "MVAU_hls_8", "Thresholding_hls_7", "MVAU_hls_9", "ElementwiseAdd_hls_0"],
                    "pblock" : "SLICE_X82Y300:SLICE_X96Y359 DSP48E2_X15Y120:DSP48E2_X19Y143 RAMB18_X8Y120:RAMB18_X9Y143 RAMB36_X8Y60:RAMB36_X9Y71"
                }
            }
        }
    }
}
